defconQt/__init__.py
defconQt/controls/__init__.py
defconQt/controls/baseCodeEditor.py
defconQt/controls/colorVignette.py
defconQt/controls/featureCodeEditor.py
defconQt/controls/glyphCellView.py
defconQt/controls/glyphContextView.py
defconQt/controls/glyphLineView.py
defconQt/controls/glyphNameComboBox.py
defconQt/controls/glyphSequenceEdit.py
defconQt/controls/glyphView.py
defconQt/controls/listView.py
defconQt/controls/roundedButtonSet.py
defconQt/representationFactories/__init__.py
defconQt/representationFactories/glyphCellFactory.py
defconQt/representationFactories/glyphViewFactory.py
defconQt/representationFactories/qPainterPathFactory.py
defconQt/tools/__init__.py
defconQt/tools/drawing.py
defconQt/tools/glyphsMimeData.py
defconQt/tools/platformSpecific.py
defconQt/tools/textSplitter.py
defconQt/windows/__init__.py
defconQt/windows/baseWindows.py
trufont/__init__.py
trufont/__main__.py
trufont/_version.py
trufont/controls/__init__.py
trufont/controls/aboutDialog.py
trufont/controls/clickLabel.py
trufont/controls/exportDialog.py
trufont/controls/fileMessageBoxes.py
trufont/controls/folderComboBox.py
trufont/controls/fontDialogs.py
trufont/controls/glyphAlignmentWidget.py
trufont/controls/glyphCanvasView.py
trufont/controls/glyphDialogs.py
trufont/controls/glyphStackWidget.py
trufont/controls/groupBox.py
trufont/controls/nameTabWidget.py
trufont/controls/pathButton.py
trufont/controls/propertiesView.py
trufont/controls/statusBar.py
trufont/controls/tabWidget.py
trufont/controls/toolBar.py
trufont/drawingTools/__init__.py
trufont/drawingTools/baseTool.py
trufont/drawingTools/knifeTool.py
trufont/drawingTools/penTool.py
trufont/drawingTools/rulerTool.py
trufont/drawingTools/selectionTool.py
trufont/drawingTools/shapesTool.py
trufont/drawingTools/textTool.py
trufont/objects/__init__.py
trufont/objects/application.py
trufont/objects/defcon.py
trufont/objects/extension.py
trufont/objects/icons.py
trufont/objects/layoutEngine.py
trufont/objects/layoutManager.py
trufont-0.6.6.dist-info/LICENSE.GPLv3
trufont-0.6.6.dist-info/LICENSE.LGPLv3
trufont-0.6.6.dist-info/METADATA
trufont-0.6.6.dist-info/WHEEL
trufont-0.6.6.dist-info/entry_points.txt
trufont-0.6.6.dist-info/top_level.txt
trufont-0.6.6.dist-info/RECORD
