Metadata-Version: 2.1
Name: trufont
Version: 0.6.6
Summary: TruFont, a modular and cross-platform font editor.
Home-page: http://trufont.github.io
Author: Adrien Tétar
Author-email: adri-from-59@hotmail.fr
License: GNU LGPL v3/GNU GPL v3
Platform: Linux
Platform: Win32
Platform: Mac OS X
Classifier: Development Status :: 4 - Beta
Classifier: Environment :: X11 Applications :: Qt
Classifier: Intended Audience :: Developers
Classifier: License :: OSI Approved :: GNU General Public License v3 (GPLv3)
Classifier: License :: OSI Approved :: GNU Lesser General Public License v3 (LGPLv3)
Classifier: Operating System :: MacOS :: MacOS X
Classifier: Operating System :: Microsoft :: Windows
Classifier: Operating System :: POSIX :: Linux
Classifier: Programming Language :: Python :: 3
Classifier: Programming Language :: Python :: 3.6
Classifier: Programming Language :: Python :: 3.7
Classifier: Topic :: Multimedia :: Graphics :: Editors :: Vector-Based
Classifier: Topic :: Text Processing :: Fonts
Requires-Python: >=3.6
Requires-Dist: booleanOperations (>=0.7.0)
Requires-Dist: defcon (>=0.6.0)
Requires-Dist: fonttools[lxml,type1,ufo,unicode,woff] (>=4.0.0)
Requires-Dist: hsluv (>=0.0.2)
Requires-Dist: pyqt5 (>=5.5.0)
Requires-Dist: ufo-extractor (>=0.3.0)
Requires-Dist: ufo2ft (>=0.5.3)
Requires-Dist: pyobjc-framework-cocoa (>=6.2) ; sys_platform == "darwin"
